<?xml version="1.0" encoding="utf-8" ?>
<dwsync>
<file name="Font.php" server="avido.udea.edu.co//backup/admondoc/dedo/" local="131079678490000000" remote="131079678490000000" />
<file name="Cell.php" server="avido.udea.edu.co//backup/admondoc/dedo/" local="131079678490000000" remote="131079678490000000" />
<file name="Image.php" server="avido.udea.edu.co//backup/admondoc/dedo/" local="131079678490000000" remote="131079678490000000" />
<file name="TableFull.php" server="avido.udea.edu.co//backup/admondoc/dedo/" local="131079678490000000" remote="131079678490000000" />
<file name="TOC.php" server="avido.udea.edu.co//backup/admondoc/dedo/" local="131079678490000000" remote="131079678490000000" />
<file name="Table.php" server="avido.udea.edu.co//backup/admondoc/dedo/" local="131079678490000000" remote="131079678490000000" />
<file name="Paragraph.php" server="avido.udea.edu.co//backup/admondoc/dedo/" local="131079678490000000" remote="131079678490000000" />
<file name="ListItem.php" server="avido.udea.edu.co//backup/admondoc/dedo/" local="131079678490000000" remote="131079678490000000" />
</dwsync>