<?xml version="1.0" encoding="utf-8" ?>
<dwsync>
<file name="LineChartTest.php" server="avido.udea.edu.co//backup/admondoc/dedo/" local="131133331810000000" remote="131133331810000000" />
<file name="HorizontalBarChartTest.php" server="avido.udea.edu.co//backup/admondoc/dedo/" local="131133331810000000" remote="131133331810000000" />
<file name="MultipleLineChartTest.php" server="avido.udea.edu.co//backup/admondoc/dedo/" local="131133331810000000" remote="131133331810000000" />
<file name="MultipleVerticalBarChartTest.php" server="avido.udea.edu.co//backup/admondoc/dedo/" local="131133331810000000" remote="131133331810000000" />
<file name="MultipleHorizontalBarChartTest.php" server="avido.udea.edu.co//backup/admondoc/dedo/" local="131133331810000000" remote="131133331810000000" />
<file name="DirectPNGOutputTest.php" server="avido.udea.edu.co//backup/admondoc/dedo/" local="131133331800000000" remote="131133331800000000" />
<file name="PieChartTest.php" server="avido.udea.edu.co//backup/admondoc/dedo/" local="131133331810000000" remote="131133331810000000" />
<file name="VerticalBarChartTest.php" server="avido.udea.edu.co//backup/admondoc/dedo/" local="131133331810000000" remote="131133331810000000" />
<file name="PieChartColorTest.php" server="avido.udea.edu.co//backup/admondoc/dedo/" local="131133331810000000" remote="131133331810000000" />
</dwsync>